AUTHORS.rst
CONTRIBUTING.rst
HISTORY.rst
LICENSE
MANIFEST.in
README.rst
setup.cfg
setup.py
docs/Makefile
docs/authors.rst
docs/conf.py
docs/contributing.rst
docs/history.rst
docs/index.rst
docs/installation.rst
docs/make.bat
docs/readme.rst
docs/usage.rst
smartgarden_x/__init__.py
smartgarden_x/sensors.py
smartgarden_x/smartgarden_x.py
smartgarden_x.egg-info/PKG-INFO
smartgarden_x.egg-info/SOURCES.txt
smartgarden_x.egg-info/dependency_links.txt
smartgarden_x.egg-info/not-zip-safe
smartgarden_x.egg-info/top_level.txt
tests/__init__.py
tests/test_smartgarden_x.py