Metadata-Version: 1.2
Name: smartgarden-x
Version: 0.2.0
Summary: This package contains functions to monitor and maintain the conditions of a greenhouse ga
Home-page: https://github.com/SabeloX/smartgarden_x
Author: Sabelo Mtetwa
Author-email: sabelomtw@gmail.com
License: MIT license
Keywords: smartgarden_x
Platform: UNKNOWN
Classifier: Development Status :: 2 - Pre-Alpha
Classifier: Intended Audience :: Developers
Classifier: License :: OSI Approved :: MIT License
Classifier: Natural Language :: English
Classifier: Programming Language :: Python :: 3
Classifier: Programming Language :: Python :: 3.5
Classifier: Programming Language :: Python :: 3.6
Classifier: Programming Language :: Python :: 3.7
Classifier: Programming Language :: Python :: 3.8
Requires-Python: >=3.5
